Metadata-Version: 1.0
Name: satiyam-simple-stats
Version: 0.2
Summary: Gaussian and Binomial Distributions
Home-page: UNKNOWN
Author: UNKNOWN
Author-email: UNKNOWN
License: UNKNOWN
Platform: UNKNOWN
